donware/__init__.py
donware/src/__init__.py
donware/src/utils/__init__.py
donware/src/utils/terminal.py
donware-0.2.0.dist-info/licenses/LICENSE
donware-0.2.0.dist-info/METADATA
donware-0.2.0.dist-info/WHEEL
donware-0.2.0.dist-info/top_level.txt
donware-0.2.0.dist-info/RECORD
