Metadata-Version: 2.4
Name: donware
Version: 0.2.0
Summary: Don's personal toolkits for data science and machine learning.
Home-page: https://github.com/Don-Yin/donware
Author: Don Yin
Author-email: Don_Yin@outlook.com
Classifier: Programming Language :: Python :: 3
Classifier: License :: OSI Approved :: MIT License
Classifier: Operating System :: OS Independent
Requires-Python: >=3.12
License-File: LICENSE
Dynamic: author
Dynamic: author-email
Dynamic: classifier
Dynamic: description
Dynamic: description-content-type
Dynamic: home-page
Dynamic: license-file
Dynamic: requires-python
Dynamic: summary
